README.md
setup.cfg
setup.py
Topsis_401703010/tops.py
Topsis_401703010.egg-info/PKG-INFO
Topsis_401703010.egg-info/SOURCES.txt
Topsis_401703010.egg-info/dependency_links.txt
Topsis_401703010.egg-info/entry_points.txt
Topsis_401703010.egg-info/requires.txt
Topsis_401703010.egg-info/top_level.txt