Metadata-Version: 2.1
Name: Topsis-401703010
Version: 1.0
Summary: A Python package to implement Topsis 
Home-page: https://github.com/midhajiya
Author: Jiya Midha
Author-email: midhajiya@gmail.com
License: MIT
Platform: UNKNOWN
Classifier: License :: OSI Approved :: MIT License
Classifier: Programming Language :: Python :: 3
Classifier: Programming Language :: Python :: 3.7
